danling/__init__.py
danling/_version.py
danling/registry.py
danling/typing.py
danling/metrics/__init__.py
danling/metrics/average_meter.py
danling/metrics/functional.py
danling/metrics/metric_meter.py
danling/metrics/metrics.py
danling/metrics/preprocesses.py
danling/metrics/utils.py
danling/modules/__init__.py
danling/modules/mlp/__init__.py
danling/modules/mlp/dense.py
danling/modules/mlp/mlp.py
danling/modules/transformer/__init__.py
danling/modules/transformer/decoder.py
danling/modules/transformer/encoder.py
danling/modules/transformer/attention/__init__.py
danling/modules/transformer/attention/multihead_attention.py
danling/modules/transformer/attention/simple_attention.py
danling/modules/transformer/ffn/__init__.py
danling/modules/transformer/ffn/fcn.py
danling/modules/transformer/pos_embed/__init__.py
danling/modules/transformer/pos_embed/pos_embed.py
danling/optim/__init__.py
danling/optim/lr_scheduler/__init__.py
danling/optim/lr_scheduler/lr_scheduler.py
danling/runner/README.md
danling/runner/__init__.py
danling/runner/accelerate_runner.py
danling/runner/base_runner.py
danling/runner/defaults.py
danling/runner/state.py
danling/runner/torch_runner.py
danling/runner/utils.py
danling/tensors/__init__.py
danling/tensors/functional.py
danling/tensors/nested_tensor.py
danling/tensors/utils.py
danling/utils/__init__.py
danling/utils/basex.py
danling/utils/contextmanagers.py
danling/utils/decorators.py
danling/utils/defaults.py
danling/utils/descriptors.py
danling/utils/distributed.py
danling/utils/io.py
danling/utils/lists.py
danling-0.3.13.dist-info/LICENSE
danling-0.3.13.dist-info/LICENSE.header
danling-0.3.13.dist-info/METADATA
danling-0.3.13.dist-info/WHEEL
danling-0.3.13.dist-info/top_level.txt
danling-0.3.13.dist-info/RECORD
