Metadata-Version: 2.2
Name: danling
Version: 0.3.13
Summary: Scaffold for experienced Machine Learning Researchers
Author-email: Zhiyuan Chen <this@zyc.ai>
Maintainer-email: Zhiyuan Chen <this@zyc.ai>
License: Unlicense OR AGPL-3.0-or-later OR GPL-2.0-or-later OR BSD-4-Clause OR MIT OR Apache-2.0
Project-URL: documentation, https://danling.org
Project-URL: homepage, https://danling.org
Project-URL: repository, https://github.com/ZhiyuanChen/DanLing
Keywords: Artificial Intelligence,Deep Learning,Machine Learning
Classifier: Development Status :: 2 - Pre-Alpha
Classifier: Intended Audience :: Developers
Classifier: Intended Audience :: Education
Classifier: Intended Audience :: Science/Research
Classifier: Operating System :: OS Independent
Classifier: Programming Language :: Python :: 3 :: Only
Classifier: Programming Language :: Python :: 3.8
Classifier: Programming Language :: Python :: 3.9
Classifier: Programming Language :: Python :: 3.10
Classifier: Programming Language :: Python :: 3.11
Classifier: Programming Language :: Python :: 3.12
Classifier: Topic :: Scientific/Engineering :: Artificial Intelligence
Requires-Python: >=3.8
License-File: LICENSE
License-File: LICENSE.header
Requires-Dist: cached-property; python_version < "3.8"
Requires-Dist: chanfig>=0.0.105
Requires-Dist: gitpython
Requires-Dist: lazy-imports
Requires-Dist: strenum; python_version < "3.11"
Requires-Dist: tqdm
Provides-Extra: jax
Requires-Dist: flax; extra == "jax"
Requires-Dist: jax; extra == "jax"
Provides-Extra: tensorflow
Requires-Dist: tensorflow; extra == "tensorflow"
Provides-Extra: torch
Requires-Dist: accelerate; extra == "torch"
Requires-Dist: torch; extra == "torch"
Requires-Dist: torcheval; extra == "torch"
Requires-Dist: torchmetrics; extra == "torch"
